README.md
setup.py
crafter/__init__.py
crafter/constants.py
crafter/data.yaml
crafter/engine.py
crafter/env.py
crafter/objects.py
crafter/recorder.py
crafter/run_gui.py
crafter/run_random.py
crafter/run_terrain.py
crafter/worldgen.py
crafter.egg-info/PKG-INFO
crafter.egg-info/SOURCES.txt
crafter.egg-info/dependency_links.txt
crafter.egg-info/entry_points.txt
crafter.egg-info/requires.txt
crafter.egg-info/top_level.txt
crafter/assets/1.png
crafter/assets/2.png
crafter/assets/3.png
crafter/assets/4.png
crafter/assets/5.png
crafter/assets/6.png
crafter/assets/7.png
crafter/assets/8.png
crafter/assets/9.png
crafter/assets/arrow-down.png
crafter/assets/arrow-left.png
crafter/assets/arrow-right.png
crafter/assets/arrow-up.png
crafter/assets/coal.png
crafter/assets/cow.png
crafter/assets/debug-2.png
crafter/assets/debug-3.png
crafter/assets/debug.png
crafter/assets/diamond.png
crafter/assets/drink.png
crafter/assets/energy.png
crafter/assets/fence.png
crafter/assets/food.png
crafter/assets/furnace.png
crafter/assets/grass.png
crafter/assets/health.png
crafter/assets/iron.png
crafter/assets/iron_pickaxe.png
crafter/assets/iron_sword.png
crafter/assets/lava.png
crafter/assets/leaves.png
crafter/assets/log.png
crafter/assets/path.png
crafter/assets/plant-ripe.png
crafter/assets/plant-young.png
crafter/assets/plant.png
crafter/assets/player-down.png
crafter/assets/player-left.png
crafter/assets/player-right.png
crafter/assets/player-sleep.png
crafter/assets/player-up.png
crafter/assets/player.png
crafter/assets/sand.png
crafter/assets/sapling.png
crafter/assets/skeleton.png
crafter/assets/stone.png
crafter/assets/stone_pickaxe.png
crafter/assets/stone_sword.png
crafter/assets/table.png
crafter/assets/tree.png
crafter/assets/unknown.png
crafter/assets/water.png
crafter/assets/wood.png
crafter/assets/wood_pickaxe.png
crafter/assets/wood_sword.png
crafter/assets/zombie.png