Metadata-Version: 2.1
Name: crafter
Version: 1.6.0
Summary: Open world survival game for reinforcement learning.
Home-page: http://github.com/danijar/crafter
License: UNKNOWN
Platform: UNKNOWN
Classifier: Intended Audience :: Science/Research
Classifier: License :: OSI Approved :: MIT License
Classifier: Programming Language :: Python :: 3
Classifier: Topic :: Games/Entertainment
Classifier: Topic :: Scientific/Engineering :: Artificial Intelligence
Provides-Extra: gui
